manuelharofulgencio2/__init__.py
manuelharofulgencio2/opengate_client.py
manuelharofulgencio2/ai_models/__init__.py
manuelharofulgencio2/ai_models/ai_models.py
manuelharofulgencio2/ai_pipelines/__init__.py
manuelharofulgencio2/ai_pipelines/ai_pipelines.py
manuelharofulgencio2/ai_transformers/__init__.py
manuelharofulgencio2/ai_transformers/ai_transformers.py
manuelharofulgencio2/datapoints/__init__.py
manuelharofulgencio2/datapoints/datapoints.py
manuelharofulgencio2/datasets/__init__.py
manuelharofulgencio2/datasets/datasets.py
manuelharofulgencio2/entities/__init__.py
manuelharofulgencio2/entities/entities.py
manuelharofulgencio2/rules/__init__.py
manuelharofulgencio2/rules/rules.py
manuelharofulgencio2/test/__init__.py
manuelharofulgencio2/test/ownworld.py
manuelharofulgencio2/test/test_steps_cucumber.py
manuelharofulgencio2/timeseries/__init__.py
manuelharofulgencio2/timeseries/timeseries.py
manuelharofulgencio2-1.0.0.dist-info/METADATA
manuelharofulgencio2-1.0.0.dist-info/WHEEL
manuelharofulgencio2-1.0.0.dist-info/top_level.txt
manuelharofulgencio2-1.0.0.dist-info/RECORD
